powerpoint_server.py
office_editor_mcp-0.2.1.dist-info/licenses/LICENSE
office_editor_mcp-0.2.1.dist-info/METADATA
office_editor_mcp-0.2.1.dist-info/WHEEL
office_editor_mcp-0.2.1.dist-info/entry_points.txt
office_editor_mcp-0.2.1.dist-info/top_level.txt
office_editor_mcp-0.2.1.dist-info/RECORD
