Metadata-Version: 2.4
Name: office_editor_mcp
Version: 0.2.1
License-File: LICENSE
Requires-Dist: annotated-types>=0.7.0
Requires-Dist: anyio>=4.9.0
Requires-Dist: click>=8.2.1
Requires-Dist: Flask>=3.1.1
Requires-Dist: httpcore>=1.0.9
Requires-Dist: httpx>=0.28.1
Requires-Dist: httpx-sse>=0.4.0
Requires-Dist: itsdangerous>=2.2.0
Requires-Dist: Jinja2>=3.1.6
Requires-Dist: lxml>=5.4.0
Requires-Dist: mcp>=1.9.3
Requires-Dist: pillow>=11.2.1
Requires-Dist: pydantic>=2.11.5
Requires-Dist: pydantic-settings>=2.9.1
Requires-Dist: pydantic_core>=2.33.2
Requires-Dist: python-docx>=1.1.2
Requires-Dist: python-dotenv>=1.1.0
Requires-Dist: python-multipart>=0.0.20
Requires-Dist: python-pptx>=1.0.2
Requires-Dist: sniffio>=1.3.1
Requires-Dist: sse-starlette>=2.3.6
Requires-Dist: starlette>=0.47.0
Requires-Dist: typing-inspection>=0.4.1
Requires-Dist: typing_extensions>=4.14.0
Requires-Dist: uvicorn>=0.34.3
Requires-Dist: Werkzeug>=3.1.3
Requires-Dist: XlsxWriter>=3.2.4
Requires-Dist: oss2>=2.19.1
Requires-Dist: loguru>=0.7.3
Dynamic: license-file
Dynamic: requires-dist
